pade/__init__.py
pade/acl/__init__.py
pade/acl/aid.py
pade/acl/filters.py
pade/acl/messages.py
pade/behaviours/__init__.py
pade/behaviours/protocols.py
pade/cli/__init__.py
pade/cli/pade_cmd.py
pade/core/__init__.py
pade/core/agent.py
pade/core/new_ams.py
pade/core/peer.py
pade/core/sniffer.py
pade/db/__init__.py
pade/drivers/__init__.py
pade/drivers/mosaik_driver.py
pade/misc/__init__.py
pade/misc/common.py
pade/misc/utility.py
pade/web/__init__.py
pade/web/flask_server.py
pade/web/static/__init__.py
pade/web/static/pade_logo.png
pade/web/static/pade_logo_favicon.png
pade/web/static/pade_logo_header.png
pade/web/static/raphael-min.js
pade/web/static/sequence-diagram-min.js
pade/web/static/signin.css
pade/web/static/snap.svg-min.js
pade/web/static/underscore-min.js
pade/web/static/webfont.js
pade/web/templates/__init__.py
pade/web/templates/agent_messages.html
pade/web/templates/agentes.html
pade/web/templates/diagrams.html
pade/web/templates/footer.html
pade/web/templates/header.html
pade/web/templates/index.html
pade/web/templates/login.html
pade/web/templates/logout.html
pade/web/templates/manage_users.html
pade/web/templates/message.html
pade/web/templates/messages.html
pade/web/templates/messagesDiagrams.html
pade/web/templates/messagesFiltered.html
pade/web/templates/messagesList.html
pade/web/templates/messagesTable.html
pade/web/templates/register_users.html
pade/web/templates/remote_sessions.html
pade/web/templates/sessions.html
pade-2.2.4.dist-info/LICENSE
pade-2.2.4.dist-info/METADATA
pade-2.2.4.dist-info/WHEEL
pade-2.2.4.dist-info/entry_points.txt
pade-2.2.4.dist-info/top_level.txt
pade-2.2.4.dist-info/RECORD
