Metadata-Version: 2.1
Name: pade
Version: 2.2.4
Summary: Framework for multiagent systems development in Python
Home-page: http://pade.readthedocs.org
Author: Lucas S Melo
Author-email: lucassmelo@dee.ufc.br
License: MIT
Keywords: multiagent distributed systems
Platform: UNKNOWN
Classifier: Development Status :: 4 - Beta
Classifier: Intended Audience :: Developers
Classifier: Topic :: Software Development :: Build Tools
Classifier: License :: OSI Approved :: MIT License
Classifier: Operating System :: OS Independent
Classifier: Programming Language :: Python :: 3
Classifier: Programming Language :: Python :: 3.7
